collibra_management_console/__init__.py
collibra_management_console/api_client.py
collibra_management_console/configuration.py
collibra_management_console/rest.py
collibra_management_console/api/__init__.py
collibra_management_console/api/backup_api.py
collibra_management_console/api/backup_schedule_api.py
collibra_management_console/api/console_configuration_api.py
collibra_management_console/api/console_saml_api.py
collibra_management_console/api/dgc_configuration_api.py
collibra_management_console/api/dgc_license_api.py
collibra_management_console/api/dgc_logger_api.py
collibra_management_console/api/dgc_saml_api.py
collibra_management_console/api/environment_api.py
collibra_management_console/api/jobserver_configuration_api.py
collibra_management_console/api/jvm_api.py
collibra_management_console/api/managed_services_api.py
collibra_management_console/api/node_api.py
collibra_management_console/api/node_configuration_api.py
collibra_management_console/api/restore_api.py
collibra_management_console/api/service_provider_api.py
collibra_management_console/api/support_api.py
collibra_management_console/api/user_api.py
collibra_management_console/models/__init__.py
collibra_management_console/models/ajp_connector_configuration.py
collibra_management_console/models/application_server_configuration.py
collibra_management_console/models/attribute_fields.py
collibra_management_console/models/backup_async_body.py
collibra_management_console/models/backup_body.py
collibra_management_console/models/backup_configuration.py
collibra_management_console/models/backup_information_model.py
collibra_management_console/models/backup_model.py
collibra_management_console/models/backup_retry_configuration.py
collibra_management_console/models/backup_schedule_configuration.py
collibra_management_console/models/backup_schedule_create_request.py
collibra_management_console/models/backup_schedule_model.py
collibra_management_console/models/backup_schedule_model_server_time_zone_offset.py
collibra_management_console_100-1.0.0.dist-info/METADATA
collibra_management_console_100-1.0.0.dist-info/WHEEL
collibra_management_console_100-1.0.0.dist-info/top_level.txt
collibra_management_console_100-1.0.0.dist-info/RECORD
