Metadata-Version: 2.1
Name: collibra-management-console-100
Version: 1.0.0
Summary: Collibra Management Console
Home-page: 
Author-email: 
Keywords: Swagger,Collibra Management Console
Requires-Dist: urllib3 (>=1.15)
Requires-Dist: six (>=1.10)
Requires-Dist: certifi
Requires-Dist: python-dateutil
